ssf/__init__.py
ssf/__main__.py
ssf/edge_name.txt
ssf/knowledge.json
ssf/app/server.py
ssf/app/static/favicon.ico
ssf/app/static/index.html
ssf/app/static/css/style.css
ssf/app/static/js/app.js
ssf/app/static/js/cytoscape.min.js
ssf/app/static/js/threat_graph.js
ssf/core/__init__.py
ssf/core/ai.py
ssf/core/ai_anthropic.py
ssf/core/ai_generic.py
ssf/core/ai_local.py
ssf/core/banner.py
ssf/core/base.py
ssf/core/ci.py
ssf/core/compiler.py
ssf/core/config.py
ssf/core/diff.py
ssf/core/exploit.py
ssf/core/knowledge.py
ssf/core/plugin_manager.py
ssf/core/report.py
ssf/core/scanner_manager.py
ssf/core/session.py
ssf/core/tamper.py
ssf/core/utils.py
ssf/core/wizard.py
ssf/core/data/user_agents.txt
ssf/plugins/auth_misconfig.py
ssf/plugins/cors_exploit.py
ssf/plugins/dummy_plugin.py
ssf/plugins/security_headers.py
ssf/plugins/sensitive_artifacts.py
ssf/plugins/storage_malware.py
ssf/prompt/data.json
ssf/scanners/__init__.py
ssf/scanners/auth.py
ssf/scanners/brute.py
ssf/scanners/extensions.py
ssf/scanners/functions.py
ssf/scanners/graphql.py
ssf/scanners/jwt_attack.py
ssf/scanners/openapi.py
ssf/scanners/postgres.py
ssf/scanners/postgrest_fuzzer.py
ssf/scanners/realtime.py
ssf/scanners/rls.py
ssf/scanners/rpc.py
ssf/scanners/sast.py
ssf/scanners/storage.py
ssf/scanners/table_lists.txt
supabase_audit_framework-1.2.17.dist-info/licenses/LICENSE
supabase_audit_framework-1.2.17.dist-info/METADATA
supabase_audit_framework-1.2.17.dist-info/WHEEL
supabase_audit_framework-1.2.17.dist-info/entry_points.txt
supabase_audit_framework-1.2.17.dist-info/top_level.txt
supabase_audit_framework-1.2.17.dist-info/RECORD
