Metadata-Version: 2.4
Name: supabase-audit-framework
Version: 1.2.17
Summary: Supabase Audit Framework
Author-email: Author <tigerzaza5678@gmail.com>
Classifier: Programming Language :: Python :: 3
Classifier: License :: OSI Approved :: MIT License
Classifier: Operating System :: OS Independent
Requires-Python: >=3.9
License-File: LICENSE
Requires-Dist: httpx
Requires-Dist: rich
Requires-Dist: pydantic
Requires-Dist: google-generativeai
Requires-Dist: python-dotenv
Requires-Dist: websockets
Requires-Dist: fastapi==0.124.0
Requires-Dist: uvicorn
Requires-Dist: python-multipart==0.0.18
Requires-Dist: curl_cffi==0.7.0b6
Requires-Dist: PyJWT
Requires-Dist: starlette==0.49.1
Requires-Dist: h11==0.16.0
Requires-Dist: zipp==3.19.1
Requires-Dist: anyio==4.4.0
Dynamic: license-file
